odoo10_addon_account_balance_ebp_csv_export-10.0.1.0.0.99.dev8-py2.7-nspkg.pth
odoo/addons/account_balance_ebp_csv_export/README.rst
odoo/addons/account_balance_ebp_csv_export/__init__.py
odoo/addons/account_balance_ebp_csv_export/__manifest__.py
odoo/addons/account_balance_ebp_csv_export/report.xml
odoo/addons/account_balance_ebp_csv_export/i18n/account_balance_ebp_csv_export.pot
odoo/addons/account_balance_ebp_csv_export/i18n/am.po
odoo/addons/account_balance_ebp_csv_export/i18n/ar.po
odoo/addons/account_balance_ebp_csv_export/i18n/bg.po
odoo/addons/account_balance_ebp_csv_export/i18n/bs.po
odoo/addons/account_balance_ebp_csv_export/i18n/ca.po
odoo/addons/account_balance_ebp_csv_export/i18n/cs.po
odoo/addons/account_balance_ebp_csv_export/i18n/da.po
odoo/addons/account_balance_ebp_csv_export/i18n/de.po
odoo/addons/account_balance_ebp_csv_export/i18n/el_GR.po
odoo/addons/account_balance_ebp_csv_export/i18n/en_AU.po
odoo/addons/account_balance_ebp_csv_export/i18n/en_GB.po
odoo/addons/account_balance_ebp_csv_export/i18n/es.po
odoo/addons/account_balance_ebp_csv_export/i18n/es_AR.po
odoo/addons/account_balance_ebp_csv_export/i18n/es_CL.po
odoo/addons/account_balance_ebp_csv_export/i18n/es_CO.po
odoo/addons/account_balance_ebp_csv_export/i18n/es_CR.po
odoo/addons/account_balance_ebp_csv_export/i18n/es_DO.po
odoo/addons/account_balance_ebp_csv_export/i18n/es_EC.po
odoo/addons/account_balance_ebp_csv_export/i18n/es_ES.po
odoo/addons/account_balance_ebp_csv_export/i18n/es_MX.po
odoo/addons/account_balance_ebp_csv_export/i18n/es_PE.po
odoo/addons/account_balance_ebp_csv_export/i18n/et.po
odoo/addons/account_balance_ebp_csv_export/i18n/eu.po
odoo/addons/account_balance_ebp_csv_export/i18n/fa.po
odoo/addons/account_balance_ebp_csv_export/i18n/fi.po
odoo/addons/account_balance_ebp_csv_export/i18n/fr.po
odoo/addons/account_balance_ebp_csv_export/i18n/fr_CA.po
odoo/addons/account_balance_ebp_csv_export/i18n/fr_CH.po
odoo10_addon_account_balance_ebp_csv_export-10.0.1.0.0.99.dev8.dist-info/METADATA
odoo10_addon_account_balance_ebp_csv_export-10.0.1.0.0.99.dev8.dist-info/RECORD
odoo10_addon_account_balance_ebp_csv_export-10.0.1.0.0.99.dev8.dist-info/WHEEL
odoo10_addon_account_balance_ebp_csv_export-10.0.1.0.0.99.dev8.dist-info/namespace_packages.txt
odoo10_addon_account_balance_ebp_csv_export-10.0.1.0.0.99.dev8.dist-info/top_level.txt
